cuga/__init__.py
cuga/cli.py
cuga/config.py
cuga/sdk.py
cuga/settings.toml
cuga/backend/__init__.py
cuga/backend/activity_tracker/__init__.py
cuga/backend/activity_tracker/join_tool.py
cuga/backend/activity_tracker/render_helper.py
cuga/backend/activity_tracker/tracker.py
cuga/backend/browser_env/__init__.py
cuga/backend/browser_env/browser/__init__.py
cuga/backend/browser_env/browser/chat_async.py
cuga/backend/browser_env/browser/env.py
cuga/backend/browser_env/browser/extension_env_async.py
cuga/backend/browser_env/browser/gym_env.py
cuga/backend/browser_env/browser/gym_env_async.py
cuga/backend/browser_env/browser/open_ended_async.py
cuga/backend/browser_env/browser/utils.py
cuga/backend/browser_env/browser/utils_async.py
cuga/backend/browser_env/browser/gym_obs/__init__.py
cuga/backend/browser_env/browser/gym_obs/extract_chrome_extension.py
cuga/backend/browser_env/browser/gym_obs/http_stream_comm.py
cuga/backend/browser_env/browser/gym_obs/obs.py
cuga/backend/browser_env/browser/gym_obs/obs_async.py
cuga/backend/browser_env/browser/gym_obs/websocket_server.py
cuga/backend/browser_env/browser/gym_obs/javascript/frame_mark_elements.js
cuga/backend/browser_env/browser/gym_obs/javascript/frame_unmark_elements.js
cuga/backend/browser_env/page_understanding/__init__.py
cuga/backend/browser_env/page_understanding/extension_processor.py
cuga/backend/browser_env/page_understanding/pu_extractor.py
cuga/backend/browser_env/page_understanding/pu_extractor_chrome_extension.py
cuga/backend/browser_env/page_understanding/pu_processor.py
cuga/backend/browser_env/page_understanding/pu_transform.py
cuga/backend/browser_env/page_understanding/extractor_utils/__init__.py
cuga/backend/browser_env/page_understanding/extractor_utils/extract_async.py
cuga/backend/browser_env/page_understanding/extractor_utils/javascript/frame_mark_elements.js
cuga/backend/browser_env/page_understanding/extractor_utils/javascript/frame_unmark_elements.js
cuga-0.2.8.dist-info/licenses/LICENSE
cuga-0.2.8.dist-info/METADATA
cuga-0.2.8.dist-info/WHEEL
cuga-0.2.8.dist-info/entry_points.txt
cuga-0.2.8.dist-info/top_level.txt
cuga-0.2.8.dist-info/RECORD
