Metadata-Version: 2.4
Name: cuga
Version: 0.2.8
Summary: CUGA is an open-source generalist agent for the enterprise, supporting complex task execution on web and APIs, OpenAPI/MCP integrations, composable architecture, reasoning modes, and policy-aware features.
License-Expression: Apache-2.0
Project-URL: Homepage, https://cuga.dev
Project-URL: Repository, https://github.com/cuga-project/cuga-agent
Requires-Python: <3.14,>=3.10
License-File: LICENSE
Requires-Dist: langchain
Requires-Dist: langchain-ibm<1.0.0,>=0.3.9
Requires-Dist: langchain-openai
Requires-Dist: langchain-core
Requires-Dist: aiohttp
Requires-Dist: httpx
Requires-Dist: docker
Requires-Dist: langgraph
Requires-Dist: html2text
Requires-Dist: uvicorn
Requires-Dist: fastapi[standard]
Requires-Dist: langfuse
Requires-Dist: dynaconf
Requires-Dist: playwright==1.49.0
Requires-Dist: browsergym-core==0.13.0
Requires-Dist: python-dotenv
Requires-Dist: loguru
Requires-Dist: mcp[cli]>=1.23.0
Requires-Dist: psutil>=7.0.0
Requires-Dist: typer>=0.15.3
Requires-Dist: fastmcp
Requires-Dist: langchain-mcp-adapters==0.1.14
Requires-Dist: pyyaml>=6.0.3
Requires-Dist: pymilvus[milvus-lite,model]>=2.6.4
Requires-Dist: langchain-groq>=0.3.8
Requires-Dist: tavily-python
Requires-Dist: e2b-code-interpreter>=2.4.1
Requires-Dist: torch>=2.9.1
Requires-Dist: sentence-transformers>=5.1.2
Provides-Extra: evaluation
Requires-Dist: rapidfuzz; extra == "evaluation"
Dynamic: license-file
